sdrl/__init__.py
sdrl/band/__init__.py
sdrl/band/base.py
sdrl/band/error.py
sdrl/config/__init__.py
sdrl/config/base.py
sdrl/config/satellite/CBERS/CB04_MUX.yaml
sdrl/config/satellite/CBERS/CB04_WFI.yaml
sdrl/config/satellite/GF/GF1_PMS.yaml
sdrl/config/satellite/GF/GF1_WFV.yaml
sdrl/config/satellite/GF/GF2.yaml
sdrl/config/satellite/GF/GF4.yaml
sdrl/config/satellite/GF/GF6_PMS.yaml
sdrl/config/satellite/GF/GF6_WFV.yaml
sdrl/config/satellite/Landsat/Landsat8_OLI.yaml
sdrl/config/satellite/SPOT/SPOT1-4.yaml
sdrl/config/satellite/SPOT/SPOT5.yaml
sdrl/config/satellite/SPOT/SPOT6-7.yaml
sdrl/config/satellite/Sentinel/Sentinel2A.yaml
sdrl/config/satellite/Sentinel/Sentinel2B.yaml
sdrl/config/satellite/Template/ElectronicMap.yaml
sdrl/reader/__init__.py
sdrl/reader/base.py
sdrl/reader/error.py
sdrl/reader/functions.py
sdrl/reader/utils.py
sdrl-0.0.6.dist-info/LICENSE
sdrl-0.0.6.dist-info/METADATA
sdrl-0.0.6.dist-info/WHEEL
sdrl-0.0.6.dist-info/top_level.txt
sdrl-0.0.6.dist-info/RECORD
