Metadata-Version: 2.1
Name: sdrl
Version: 0.0.6
Summary: Satellite Data Read Library
Home-page: https://github.com/geoyee/SDRL
Author: geoyee
Author-email: geoyee@yeah.net
Classifier: Programming Language :: Python :: 3
Classifier: License :: OSI Approved :: MIT License
License-File: LICENSE
Requires-Dist: scikit-image
Requires-Dist: pandas
Requires-Dist: pyyaml
Requires-Dist: GDAL
